<annotation>
	<folder>images</folder>
	<filename>2021-11-05-114657.jpg</filename>
	<path>/home/yacotaco/Dokumenty/dev/ChessView/data/images/2021-11-05-114657.jpg</path>
	<source>
		<database>Unknown</database>
	</source>
	<size>
		<width>960</width>
		<height>544</height>
		<depth>3</depth>
	</size>
	<segmented>0</segmented>
	<object>
		<name>bp</name>
		<pose>Unspecified</pose>
		<truncated>0</truncated>
		<difficult>0</difficult>
		<bndbox>
			<xmin>427</xmin>
			<ymin>217</ymin>
			<xmax>464</xmax>
			<ymax>256</ymax>
		</bndbox>
	</object>
	<object>
		<name>wp</name>
		<pose>Unspecified</pose>
		<truncated>0</truncated>
		<difficult>0</difficult>
		<bndbox>
			<xmin>518</xmin>
			<ymin>215</ymin>
			<xmax>554</xmax>
			<ymax>256</ymax>
		</bndbox>
	</object>
</annotation>
